setup.py
bot/__init__.py
bot/main.py
whatsappbot.egg-info/PKG-INFO
whatsappbot.egg-info/SOURCES.txt
whatsappbot.egg-info/dependency_links.txt
whatsappbot.egg-info/entry_points.txt
whatsappbot.egg-info/requires.txt
whatsappbot.egg-info/top_level.txt