Metadata-Version: 1.1
Name: whatsappbot
Version: 0.0.1.0
Summary: whatsapp bot for advertising
Home-page: https://github.com/harshul1610/whatsapp_bot
Author: Harshul Jain
Author-email: harshulrobo@gmail.com
License: MIT
Platform: UNKNOWN
Classifier: Development Status :: 3 - Alpha
Classifier: Intended Audience :: Developers
Classifier: Topic :: Software Development :: Build Tools
Classifier: License :: OSI Approved :: MIT License
Classifier: Programming Language :: Python :: 2
Classifier: Programming Language :: Python :: 2.6
Classifier: Programming Language :: Python :: 2.7
